read_commit/__init__.py
read_commit/__version__.py
read_commit/_cargo.py
read_commit/check.py
read_commit/cli.py
read_commit/code_statistics.py
read_commit/commit.py
read_commit-2024.9.9.dist-info/METADATA
read_commit-2024.9.9.dist-info/WHEEL
read_commit-2024.9.9.dist-info/entry_points.txt
read_commit-2024.9.9.dist-info/licenses/LICENSE
read_commit-2024.9.9.dist-info/RECORD
